basenet/__init__.py
basenet/__special__.py
basenet/_names.py
basenet/database.py
basenet/__special/__init__.py
basenet/__special/_algorithms/__init__.py
basenet/__special/_algorithms/_pbmm.py
basenet/__special/_loss_functions/__init__.py
basenet/__special/_loss_functions/windowdiff.py
basenet/cluster/__init__.py
basenet/cluster/cassandra_clustering.py
basenet/cluster/ray_clustering.py
basenet/deeplearning/__init__.py
basenet/deeplearning/compiler.py
basenet/deeplearning/feeder.py
basenet/deeplearning/model.py
basenet/deployment/__init__.py
basenet/deployment/deployed.py
basenet/include/config/compilers/base_compiler.yaml
basenet/include/temp/bypass/bypass.h5
basenet/include/temp/checkpoints/model.base_model.h5
basenet/include/temp/checkpoints/model.my_first_model.h5
basenet/include/temp/logs/base_model/train/events.out.tfevents.1666889237.DESKTOP-TUNV74K.7136.0.v2
basenet/include/temp/logs/base_model/validation/events.out.tfevents.1666889246.DESKTOP-TUNV74K.7136.1.v2
basenet/include/temp/logs/my_first_model/train/events.out.tfevents.1666793528.DESKTOP-TUNV74K.11252.0.v2
basenet/include/temp/logs/my_first_model/train/events.out.tfevents.1666793546.DESKTOP-TUNV74K.5344.0.v2
basenet/include/temp/logs/my_first_model/train/events.out.tfevents.1666793577.DESKTOP-TUNV74K.3988.0.v2
basenet/include/temp/logs/my_first_model/train/events.out.tfevents.1666793718.DESKTOP-TUNV74K.1920.0.v2
basenet/include/temp/logs/my_first_model/train/events.out.tfevents.1666794917.DESKTOP-TUNV74K.6196.0.v2
basenet/include/temp/logs/my_first_model/train/events.out.tfevents.1666799291.DESKTOP-TUNV74K.1052.0.v2
basenet/include/temp/logs/my_first_model/validation/events.out.tfevents.1666793584.DESKTOP-TUNV74K.3988.1.v2
basenet/include/temp/logs/my_first_model/validation/events.out.tfevents.1666793725.DESKTOP-TUNV74K.1920.1.v2
basenet/include/temp/logs/my_first_model/validation/events.out.tfevents.1666794923.DESKTOP-TUNV74K.6196.1.v2
basenet_api-1.9.3.dist-info/LICENSE
basenet_api-1.9.3.dist-info/METADATA
basenet_api-1.9.3.dist-info/WHEEL
basenet_api-1.9.3.dist-info/top_level.txt
basenet_api-1.9.3.dist-info/RECORD
