Metadata-Version: 2.1
Name: basenet-api
Version: 1.9.3
Summary: Basenet API: A simpler way to build ML models.
Home-page: https://github.com/iTzAlver/basenet_api.git
Author: Palomo-Alonso, Alberto
Author-email: a.palomo@edu.uah
Project-URL: Documentation, https://htmlpreview.github.io/?https://github.com/iTzAlver/basenet_api/blob/main/doc/basenet.html
Project-URL: Bug Reports, https://github.com/iTzAlver/basenet_api/issues
Project-URL: Source Code, https://github.com/iTzAlver/basenet_api.git
Keywords: deeplearning,ml,api
Classifier: Development Status :: 5 - Production/Stable
Classifier: Topic :: Software Development :: Build Tools
Classifier: Programming Language :: Python :: 3
Classifier: Operating System :: OS Independent
Classifier: License :: OSI Approved :: Apache Software License
Requires-Python: >=3.6
License-File: LICENSE
Requires-Dist: tensorflow (>=2.10.0)
Requires-Dist: graphviz (>=0.20.1)
Requires-Dist: matplotlib (>=3.6.1)
Requires-Dist: future (>=0.18.2)
Requires-Dist: Pillow (>=9.2.0)
Requires-Dist: numpy (>=1.23.4)
Requires-Dist: ttkwidgets (>=0.12.1)
Requires-Dist: pydot (>=1.4.2)
Requires-Dist: keras (>=2.9.0)
Requires-Dist: setuptools (>=60.2.0)
Requires-Dist: PyYAML (>=6.0)
Requires-Dist: tensorboard (>=2.9.1)
Requires-Dist: psutil (>=5.9.3)
Requires-Dist: pynvml (>=11.4.1)
Requires-Dist: pandas (>=1.5.2)
Requires-Dist: alive-progress (>=2.4.1)
Requires-Dist: hvplot (>=0.8.2)
Requires-Dist: ray (>=2.1.0)
Requires-Dist: cassandra-driver (>=3.25.0)
Requires-Dist: panel (~=0.14.1)
Provides-Extra: dev
Requires-Dist: check-manifest ; extra == 'dev'
